README.txt
setup.py
clutchclient/__init__.py
clutchclient/main.py
clutchclient/utils.py
clutchclient.egg-info/PKG-INFO
clutchclient.egg-info/SOURCES.txt
clutchclient.egg-info/dependency_links.txt
clutchclient.egg-info/entry_points.txt
clutchclient.egg-info/not-zip-safe
clutchclient.egg-info/requires.txt
clutchclient.egg-info/top_level.txt
clutchclient/commands/__init__.py
clutchclient/commands/dev.py
clutchclient/commands/startapp.py
clutchclient/commands/startscreen.py
clutchclient/commands/upload.py
clutchclient/commands/version.py