Metadata-Version: 1.0
Name: clutchclient
Version: 0.1.8
Summary: Command-line interface to clutch.io
Home-page: http://clutch.io/
Author: Eric Florenzano
Author-email: ericflo@boilerplateinc.com
License: MIT
Platform: UNKNOWN
Classifier: Development Status :: 2 - Pre-Alpha
Classifier: Intended Audience :: Developers
Classifier: License :: OSI Approved :: MIT License
Classifier: Operating System :: MacOS :: MacOS X
Classifier: Programming Language :: Python
Classifier: Programming Language :: Python :: 2.6
Classifier: Programming Language :: Python :: 2.7
Classifier: Topic :: Internet :: WWW/HTTP
